battdeg/__init__.py
battdeg/battdeg.py
battdeg/version.py
battdeg/tests/__init__.py
battdeg/tests/test_battdeg.py
battdeg-0.1.4.dev0.dist-info/LICENSE
battdeg-0.1.4.dev0.dist-info/METADATA
battdeg-0.1.4.dev0.dist-info/WHEEL
battdeg-0.1.4.dev0.dist-info/top_level.txt
battdeg-0.1.4.dev0.dist-info/RECORD
