Metadata-Version: 2.1
Name: battdeg
Version: 0.1.4.dev0
Summary: battdeg : predict battery degradation using machine learning
Home-page: http://github.com/chintan/battdeg
Author: Shrilakshmi Bonageri, Ge Gu, Guoyao Chen, Chintan Pathak
Author-email: 
Maintainer: Chintan Pathak
Maintainer-email: chintan.pathak@gmail.com
License: MIT
Platform: OS Independent
Classifier: Development Status :: 3 - Alpha
Classifier: Environment :: Console
Classifier: Intended Audience :: Science/Research
Classifier: License :: OSI Approved :: MIT License
Classifier: Operating System :: OS Independent
Classifier: Programming Language :: Python
Classifier: Topic :: Scientific/Engineering
Requires: pandas
Requires: numpy
Requires: sklearn
Requires: keras
Requires: pytest
Requires-Dist: pandas
Requires-Dist: numpy
Requires-Dist: sklearn
Requires-Dist: keras
Requires-Dist: pytest
